lti1p3platform/__init__.py
lti1p3platform/ags.py
lti1p3platform/constants.py
lti1p3platform/content_item.py
lti1p3platform/deep_linking.py
lti1p3platform/exceptions.py
lti1p3platform/jwt_helper.py
lti1p3platform/lineitem.py
lti1p3platform/ltiplatform.py
lti1p3platform/membership.py
lti1p3platform/message_launch.py
lti1p3platform/nrps.py
lti1p3platform/oidc_login.py
lti1p3platform/registration.py
lti1p3platform/request.py
lti1p3platform/response.py
lti1p3platform/result.py
lti1p3platform/score.py
lti1p3platform/service_connector.py
lti1p3platform/utils.py
lti1p3platform/framework/__init__.py
lti1p3platform/framework/django/__init__.py
lti1p3platform/framework/django/message_launch.py
lti1p3platform/framework/django/oidc_login.py
lti1p3platform/framework/django/request.py
lti1p3platform/framework/django/response.py
lti1p3platform/framework/fastapi/__init__.py
lti1p3platform/framework/fastapi/message_launch.py
lti1p3platform/framework/fastapi/oidc_login.py
lti1p3platform/framework/fastapi/request.py
lti1p3platform/framework/templates/__init__.py
lti1p3platform/framework/templates/launch.html
lti1p3platform-0.1.8.dist-info/METADATA
lti1p3platform-0.1.8.dist-info/WHEEL
lti1p3platform-0.1.8.dist-info/top_level.txt
lti1p3platform-0.1.8.dist-info/RECORD
