Metadata-Version: 2.1
Name: lti1p3platform
Version: 0.1.8
Summary: LTI 1.3 Platform implementation
Author-email: Jun Tu <jun@openlearning.com>
Classifier: Programming Language :: Python :: 3
Classifier: License :: OSI Approved :: MIT License
Classifier: Operating System :: OS Independent
Requires-Python: >=3.8
Requires-Dist: requests
Requires-Dist: PyJWT
Requires-Dist: jwcrypto
Provides-Extra: django
Requires-Dist: Django ; extra == 'django'
Requires-Dist: Jinja2 ; extra == 'django'
Requires-Dist: django-stubs ; extra == 'django'
Provides-Extra: fastapi
Requires-Dist: fastapi ; extra == 'fastapi'
Requires-Dist: Jinja2 ; extra == 'fastapi'
